tests/__init__.py
tests/test_unc2url.py
unc2url/__init__.py
unc2url/unc2url.py
unc2url-0.1.0.dist-info/METADATA
unc2url-0.1.0.dist-info/WHEEL
unc2url-0.1.0.dist-info/entry_points.txt
unc2url-0.1.0.dist-info/top_level.txt
unc2url-0.1.0.dist-info/RECORD
