Metadata-Version: 2.1
Name: unc2url
Version: 0.1.0
Summary: A UNC to URL Converter.
Home-page: https://github.com/alexanderwillner/unc2url
Author: Alexander Willner
Author-email: alex@willner.ws
License: UNKNOWN
Platform: UNKNOWN
Classifier: Development Status :: 4 - Beta
Classifier: Programming Language :: Python :: 3
Classifier: License :: OSI Approved :: Apache Software License
Classifier: Operating System :: MacOS :: MacOS X
Classifier: Natural Language :: English
Requires-Python: >=3.6
